{
    "frames": [
        {
            "filename": "blood15",
            "frame": {
                "w": 110,
                "h": 93,
                "x": 1,
                "y": 1
            },
            "anchor": {
                "x": 0.5,
                "y": 0.5
            }
        },
        {
            "filename": "blood16",
            "frame": {
                "w": 110,
                "h": 93,
                "x": 1,
                "y": 95
            },
            "anchor": {
                "x": 0.5,
                "y": 0.5
            }
        },
        {
            "filename": "blood17",
            "frame": {
                "w": 110,
                "h": 93,
                "x": 112,
                "y": 1
            },
            "anchor": {
                "x": 0.5,
                "y": 0.5
            }
        },
        {
            "filename": "blood18",
            "frame": {
                "w": 110,
                "h": 93,
                "x": 112,
                "y": 95
            },
            "anchor": {
                "x": 0.5,
                "y": 0.5
            }
        },
        {
            "filename": "blood19",
            "frame": {
                "w": 110,
                "h": 93,
                "x": 1,
                "y": 189
            },
            "anchor": {
                "x": 0.5,
                "y": 0.5
            }
        },
        {
            "filename": "blood20",
            "frame": {
                "w": 110,
                "h": 93,
                "x": 112,
                "y": 189
            },
            "anchor": {
                "x": 0.5,
                "y": 0.5
            }
        },
        {
            "filename": "blood21",
            "frame": {
                "w": 110,
                "h": 93,
                "x": 223,
                "y": 1
            },
            "anchor": {
                "x": 0.5,
                "y": 0.5
            }
        },
        {
            "filename": "blood22",
            "frame": {
                "w": 110,
                "h": 93,
                "x": 223,
                "y": 95
            },
            "anchor": {
                "x": 0.5,
                "y": 0.5
            }
        },
        {
            "filename": "blood23",
            "frame": {
                "w": 110,
                "h": 93,
                "x": 223,
                "y": 189
            },
            "anchor": {
                "x": 0.5,
                "y": 0.5
            }
        }
    ],
    "meta": {
        "description": "Atlas generado con Atlas Packer Gamma V2",
        "web": "https://gammafp.github.io/atlas-packer-phaser/"
    }
}